MANIFEST.in
README.md
setup.cfg
setup.py
andle/__init__.py
andle/android.py
andle/gradle.py
andle/http.py
andle/remote.py
andle/sdk.py
andle/version.py
andle.egg-info/PKG-INFO
andle.egg-info/SOURCES.txt
andle.egg-info/dependency_links.txt
andle.egg-info/not-zip-safe
andle.egg-info/top_level.txt
bin/andle