Metadata-Version: 1.0
Name: andle
Version: 1.5.4
Summary: android dependency sync tool
Home-page: http://github.com/Jintin/andle
Author: Jintin
Author-email: jintinapps@gmail.com
License: MIT
Keywords: android gradle config build version dependency sync
Platform: UNKNOWN
